<?xml version="1.0" encoding="utf-8"?>
<!DOCTYPE hibernate-mapping PUBLIC "-//Hibernate/Hibernate Mapping DTD 3.0//EN"
"http://www.hibernate.org/dtd/hibernate-mapping-3.0.dtd">
<!-- Mapping file autogenerated by MyEclipse Persistence Tools -->
<hibernate-mapping>
	<class name="com.bktravel.modules.tourism.entity.TourismImg" table="travel_route_img" dynamic-insert="true" lazy="true">
		<id name="id" type="java.lang.String">
			<column name="id" length="32" />
			<generator class="uuid.hex" />
		</id>
		<many-to-one name="tourism" class="com.bktravel.modules.tourism.entity.Tourism" fetch="select">
			<column name="travel_route_id" length="32" />
		</many-to-one>
		<property name="url" type="java.lang.String">
			<column name="url" length="100" />
		</property>
		<property name="name" type="java.lang.String">
			<column name="name" length="200" />
		</property>
		<property name="size" type="java.lang.Double">
			<column name="size" length="8" />
		</property>
	</class>
</hibernate-mapping>
